fintekkers/__init__.py
fintekkers/py.typed
fintekkers/models/__init__.py
fintekkers/models/portfolio/__init__.py
fintekkers/models/portfolio/portfolio_pb2.py
fintekkers/models/portfolio/portfolio_pb2.pyi
fintekkers/models/portfolio/portfolio_pb2_grpc.py
fintekkers/models/position/__init__.py
fintekkers/models/position/field_pb2.py
fintekkers/models/position/field_pb2.pyi
fintekkers/models/position/field_pb2_grpc.py
fintekkers/models/position/measure_pb2.py
fintekkers/models/position/measure_pb2.pyi
fintekkers/models/position/measure_pb2_grpc.py
fintekkers/models/position/position_filter_pb2.py
fintekkers/models/position/position_filter_pb2.pyi
fintekkers/models/position/position_filter_pb2_grpc.py
fintekkers/models/position/position_pb2.py
fintekkers/models/position/position_pb2.pyi
fintekkers/models/position/position_pb2_grpc.py
fintekkers/models/position/position_status_pb2.py
fintekkers/models/position/position_status_pb2.pyi
fintekkers/models/position/position_status_pb2_grpc.py
fintekkers/models/position/position_util_pb2.py
fintekkers/models/position/position_util_pb2.pyi
fintekkers/models/position/position_util_pb2_grpc.py
fintekkers/models/price/__init__.py
fintekkers/models/price/price_pb2.py
fintekkers/models/price/price_pb2.pyi
fintekkers/models/price/price_pb2_grpc.py
fintekkers/models/security/__init__.py
fintekkers/models/security/coupon_frequency_pb2.py
fintekkers/models/security/coupon_frequency_pb2.pyi
fintekkers/models/security/coupon_frequency_pb2_grpc.py
fintekkers/models/security/coupon_type_pb2.py
fintekkers/models/security/coupon_type_pb2.pyi
fintekkers/models/security/coupon_type_pb2_grpc.py
fintekkers/models/security/security_pb2.py
fintekkers/models/security/security_pb2.pyi
fintekkers/models/security/security_pb2_grpc.py
fintekkers/models/security/security_quantity_type_pb2.py
fintekkers/models/security/security_quantity_type_pb2.pyi
fintekkers/models/security/security_quantity_type_pb2_grpc.py
fintekkers_ledger_models-0.1.115.dist-info/METADATA
fintekkers_ledger_models-0.1.115.dist-info/WHEEL
fintekkers_ledger_models-0.1.115.dist-info/top_level.txt
fintekkers_ledger_models-0.1.115.dist-info/RECORD
