Metadata-Version: 2.1
Name: fintekkers-ledger-models
Version: 0.1.115
Summary: Fintekkers Ledger Models python package
Home-page: https://github.com/fintekkers/ledger-models
Author: David Doherty
Author-email: dave@fintekkers.org
License: MIT
Keywords: fintekkers ledger models
Classifier: Programming Language :: Python :: 3
Classifier: Operating System :: MacOS :: MacOS X
